flake8_iw/__init__.py
flake8_iw/bulk_batch_update.py
flake8_iw/constance_assignment.py
flake8_iw/constraint_check.py
flake8_iw/datetime_now.py
flake8_iw/datetime_replace_tzinfo.py
flake8_iw/factory_timezone_now.py
flake8_iw/foreign_key_check.py
flake8_iw/freeze_time.py
flake8_iw/logging.py
flake8_iw/parameterized_order.py
flake8_iw/patch_call.py
flake8_iw/plugin.py
flake8_iw/pytest_setup_class.py
flake8_iw/shared_task.py
flake8_iw/timezone_activate.py
flake8_iw/together_check.py
flake8_iw-0.0.26.dist-info/METADATA
flake8_iw-0.0.26.dist-info/WHEEL
flake8_iw-0.0.26.dist-info/entry_points.txt
flake8_iw-0.0.26.dist-info/top_level.txt
flake8_iw-0.0.26.dist-info/RECORD
