Metadata-Version: 2.1
Name: flake8-iw
Version: 0.0.26
Summary: A plugin to show lint errors for IW
Author-email: Platform <platform-engineering@instawork.com>
License: MIT
Project-URL: Homepage, http://github.com/Instawork/flake8-iw
Classifier: Framework :: Flake8
Classifier: Intended Audience :: Developers
Classifier: License :: OSI Approved :: MIT License
Classifier: Programming Language :: Python :: 3
Classifier: Topic :: Software Development :: Quality Assurance
Classifier: Operating System :: OS Independent
Requires-Dist: flake8 >=3.7
Requires-Dist: importlib-metadata >=0.9 ; python_version < "3.8"
Provides-Extra: testing
Requires-Dist: pytest ; extra == 'testing'
Requires-Dist: ipython ; extra == 'testing'
Requires-Dist: astpretty ; extra == 'testing'
Requires-Dist: build ; extra == 'testing'
Requires-Dist: twine ; extra == 'testing'
Requires-Dist: flake8 ; extra == 'testing'
